setup.py
dogepy/__init__.py
dogepy.egg-info/PKG-INFO
dogepy.egg-info/SOURCES.txt
dogepy.egg-info/dependency_links.txt
dogepy.egg-info/top_level.txt
dogepy.egg-info/zip-safe