Metadata-Version: 1.0
Name: dogepy
Version: 10.3
Summary: So doge, much art, wow
Home-page: https://github.com/laasli/doge
Author: Laasli, Morz
Author-email: morzzz007@gmail.com
License: BSD
Platform: UNKNOWN
